wise/__init__.py
wise/datetimeutils.py
wise/processorutils.py
wise/wise.py
wise_py_utils-1.9.3.dist-info/LICENSE.md
wise_py_utils-1.9.3.dist-info/METADATA
wise_py_utils-1.9.3.dist-info/WHEEL
wise_py_utils-1.9.3.dist-info/top_level.txt
wise_py_utils-1.9.3.dist-info/RECORD
