Metadata-Version: 2.1
Name: wise-py-utils
Version: 1.9.3
Summary: Python utils created by Zac the Wise
Home-page: UNKNOWN
Author: UNKNOWN
Author-email: UNKNOWN
License: UNKNOWN
Platform: UNKNOWN
Requires-Dist: psutil
